pylineaGT/__init__.py
pylineaGT/explogreg.py
pylineaGT/mvnmm.py
pylineaGT/run.py
pylineaGT/simulations.py
pylineaGT-0.2.0.dist-info/LICENSE
pylineaGT-0.2.0.dist-info/METADATA
pylineaGT-0.2.0.dist-info/WHEEL
pylineaGT-0.2.0.dist-info/top_level.txt
pylineaGT-0.2.0.dist-info/RECORD
