Metadata-Version: 2.1
Name: pylineaGT
Version: 0.2.0
Summary: A Pyro model to perform lineage inference from Gene Therapy assays
Home-page: UNKNOWN
Author: Elena Buscaroli
Author-email: ele.buscaroli@gmail.com
License: GPL-3.0
Platform: UNKNOWN
Requires-Python: >=3.6
Requires-Dist: pandas==1.3.3
Requires-Dist: pyro-api==0.1.2
Requires-Dist: pyro-ppl==1.8.0
Requires-Dist: torch==1.11.0
Requires-Dist: numpy==1.*
Requires-Dist: scikit-learn==1.0.2
